[
  {
    "@context": [
      "https://w3id.org/traceability/v1"
    ],
    "type": "EcommerceWayBillCommodityGroup",
    "commodityItemNumber": "th6cxwjkarft",
    "natureQuantityOfGoods": "A lot fo stuffed animals, and toys and other useless stuff that weighs a lot",
    "totalsCommodityGroup": {
      "type": "EcommerceWayBillTotals",
      "totalPieces": 319,
      "weight": 348430,
      "chargeableWeight": 313587,
      "weightUnit": "kg",
      "rateCharge": 0.013849426156058765,
      "totalRateCharge": {
        "type": "PriceSpecification",
        "price": 4343,
        "priceCurrency": "PKR"
      }
    }
  },
  {
    "@context": [
      "https://w3id.org/traceability/v1"
    ],
    "type": "EcommerceWayBillCommodityGroup",
    "commodityItemNumber": "uqeg10e2odgl",
    "natureQuantityOfGoods": "A lot of laptops that way a lot",
    "totalsCommodityGroup": {
      "type": "EcommerceWayBillTotals",
      "totalPieces": 752,
      "weight": 469562,
      "chargeableWeight": 422605.8,
      "weightUnit": "kg",
      "rateCharge": 0.014661417330287469,
      "totalRateCharge": {
        "type": "PriceSpecification",
        "price": 6196,
        "priceCurrency": "HKD"
      }
    }
  },
  {
    "@context": [
      "https://w3id.org/traceability/v1"
    ],
    "type": "EcommerceWayBillCommodityGroup",
    "commodityItemNumber": "hq0hd73yjpey",
    "natureQuantityOfGoods": "A lot fo stuffed animals, and toys and other useless stuff that weighs a lot",
    "totalsCommodityGroup": {
      "type": "EcommerceWayBillTotals",
      "totalPieces": 617,
      "weight": 432834,
      "chargeableWeight": 389550.60000000003,
      "weightUnit": "lb",
      "rateCharge": 0.012208940250637528,
      "totalRateCharge": {
        "type": "PriceSpecification",
        "price": 4756,
        "priceCurrency": "SDG"
      }
    }
  }
]