[
  {
    "@context": [
      "https://w3id.org/traceability/v1"
    ],
    "type": "PartOfOrder",
    "protocol": "back up",
    "matrix": "copy"
  },
  {
    "type": "PartOfOrder",
    "orderNumber": "Order#131",
    "itemsShipped": [
      {
        "type": "ItemShipped",
        "manufacturer": "Kulas Group",
        "name": "Licensed Soft Shirt",
        "description": "The beautiful range of Apple Naturalé that has an exciting mix of natural ingredients. With the Goodness of 100% Natural Ingredients",
        "productID": "OEQJF1O0L8",
        "weight": "4.076 lp",
        "height": "7.125 in",
        "width": "5.021 in",
        "depth": "2.091 in",
        "orderQuantity": 5
      },
      {
        "type": "ItemShipped",
        "manufacturer": "O'Connell and Sons",
        "name": "Ergonomic Metal Shirt",
        "description": "Boston's most advanced compression wear technology increases muscle oxygenation, stabilizes active muscles",
        "productID": "Y612BXB9MU",
        "weight": "1.423 lp",
        "height": "8.772 in",
        "width": "6.657 in",
        "depth": "7.953 in",
        "orderQuantity": 1
      }
    ],
    "monitor": "input",
    "card": "quantify",
    "matrix": "navigate",
    "driver": "compress"
  },
  {
    "array": "parse",
    "microchip": "bypass"
  }
]