[
  {
    "@context": [
      "https://w3id.org/traceability/v1"
    ],
    "type": "EcommerceWayBillRegistrationCredential",
    "wayBillID": "ACMEWayBill#1",
    "carrierName": "Bernhard - Kuphal",
    "modeOfTransport": "Air",
    "portOfEntry": {
      "type": "ShippingStop",
      "shippingStopAddress": {
        "type": "PostalAddress",
        "organizationName": "Huels Inc",
        "streetAddress": "5853 Roxane Falls",
        "addressLocality": "North Orenborough",
        "addressRegion": "Texas",
        "postalCode": "12481-7775",
        "addressCountry": "Brazil"
      },
      "carrier": {
        "type": "Organization",
        "name": "Bechtelar - Schuster",
        "description": "Re-contextualized attitude-oriented attitude",
        "address": {
          "type": "PostalAddress",
          "streetAddress": "25073 Mckenna Street",
          "addressLocality": "Wardfurt",
          "addressRegion": "Oregon",
          "postalCode": "39276",
          "addressCountry": "Uganda"
        },
        "email": "Ella.Schroeder@example.net",
        "phoneNumber": "555-273-5748",
        "faxNumber": "555-183-3330"
      },
      "vesselNumber": "ACMECarrierVessel#569",
      "arrivalDate": "2021-03-09",
      "stopType": "Departure"
    },
    "masterWayBill": "No",
    "wayBillVCID": [
      "https://vc.example.com/?queryID=0x9fDD44C3c11CF6b86baCCe6d432b6fBFa4503178EC70Faa731D9a5f7Ff1b22fF"
    ],
    "packageVCID": [
      "https://vc.example.com/?queryID=0x33f8fdDFcA2E2Afd447ead0d5a8b673bA4BB54B189beC9A6Bc371EDE8b67fAC0",
      "https://vc.example.com/?queryID=0xCa67CE001cdA1a71eF7b3d65aaa9B1A2aCC5245bCA81Fca2B0819C82f0c9EC55",
      "https://vc.example.com/?queryID=0x2980d9Cc7ce776d2D8528AFFDFcDbd6fb6Cdfa6a4A56362E912a3Ecd3c15674C",
      "https://vc.example.com/?queryID=0xbc2bA2D0AFb8Cdf10f8ECc720cAAB83Dbe4Dfd5266C4aDeA8e66d43A8a44fdE0",
      "https://vc.example.com/?queryID=0xF79a539FC442E47AF9CcB060098B6D01bb8Ed8dC22FE4A9EaeB72E96d74fdAEE",
      "https://vc.example.com/?queryID=0xF40B5A61885646FFEe1f7F885Bd9eDC3AEb4e76Ad8ad295A65E1566a83e728E1",
      "https://vc.example.com/?queryID=0xDccDe30d7eB91f69cb50Ef2eB0b8AF69bbCEaf7cbBfD9aEa68aFAff1DCFa912c"
    ],
    "certificateName": "ACME Carrier Ecommerce Way Bill Registration Certificate"
  },
  {
    "@context": [
      "https://w3id.org/traceability/v1"
    ],
    "type": "EcommerceWayBillRegistrationCredential",
    "wayBillID": "ACMEWayBill#48",
    "carrierName": "Harvey, Kuhlman and Morar",
    "modeOfTransport": "Truck",
    "portOfEntry": {
      "type": "ShippingStop",
      "shippingStopAddress": {
        "type": "PostalAddress",
        "organizationName": "Gottlieb - Toy",
        "streetAddress": "214 Grady Pass",
        "addressLocality": "Gottliebfort",
        "addressRegion": "Massachusetts",
        "postalCode": "95085-3041",
        "addressCountry": "Romania"
      },
      "carrier": {
        "type": "Organization",
        "name": "Bosco, Marks and Crooks",
        "description": "Polarised well-modulated throughput",
        "address": {
          "type": "PostalAddress",
          "streetAddress": "20310 Kozey Track",
          "addressLocality": "Ratkeside",
          "addressRegion": "Maryland",
          "postalCode": "25397",
          "addressCountry": "Albania"
        },
        "email": "Pascale25@example.com",
        "phoneNumber": "555-662-8296",
        "faxNumber": "555-943-9535"
      },
      "vesselNumber": "ACMECarrierVessel#539",
      "arrivalDate": "2021-03-09",
      "stopType": "Destination"
    },
    "masterWayBill": "No",
    "wayBillVCID": [
      "https://vc.example.com/?queryID=0xDeb2be5FAEA9c0472C1fdaC1C9aaBEEe668bE17FE7Fae7BfAeff651672ee200d"
    ],
    "packageVCID": [
      "https://vc.example.com/?queryID=0xfAA4FD6Fb5bD8231F2C1aCd145b2f6b1Fed28CAB308D7095B0a7BbcB77Bf544A",
      "https://vc.example.com/?queryID=0xb55304e4bb9CF1cfCe3Dc5D9cEfe8822a58cDf52FdFc5b7fDCF79D73b3f562A5",
      "https://vc.example.com/?queryID=0x121C837A61aE7f406AFb9B9bceFB58e0fCd81ae01adFA648Cf0BC9a64E2eE211",
      "https://vc.example.com/?queryID=0x4a74d5bD216f554A9ff04b838DFDF9B9561f6755b9B2CAC07ef4651dfF0B9473",
      "https://vc.example.com/?queryID=0xfDA963BC6B9FfEfCF142ecdbEa38A9cc60a57bcfD3ccdfb91059a66E32be7159",
      "https://vc.example.com/?queryID=0xac26EaD3f62dB6BDAd29e0CacAe5aBb50Ce11D9a66b529fFB4322c3aDbbea52E",
      "https://vc.example.com/?queryID=0xe9D2CAde162d14592D5288ECdFC9fb2cAE6Ce379Fa5B6dEe0Ff1f4C8F7F012Ce"
    ],
    "certificateName": "ACME Carrier Ecommerce Way Bill Registration Certificate"
  },
  {
    "@context": [
      "https://w3id.org/traceability/v1"
    ],
    "type": "EcommerceWayBillRegistrationCredential",
    "wayBillID": "ACMEWayBill#737",
    "carrierName": "Kessler - Murray",
    "modeOfTransport": "Sea",
    "portOfEntry": {
      "type": "ShippingStop",
      "shippingStopAddress": {
        "type": "PostalAddress",
        "organizationName": "Dibbert, Strosin and Dickens",
        "streetAddress": "14095 Brady Keys",
        "addressLocality": "South Amaniland",
        "addressRegion": "New Hampshire",
        "postalCode": "89353",
        "addressCountry": "Fiji"
      },
      "carrier": {
        "type": "Organization",
        "name": "Murphy LLC",
        "description": "Digitized encompassing artificial intelligence",
        "address": {
          "type": "PostalAddress",
          "streetAddress": "047 Roel Forks",
          "addressLocality": "Michealmouth",
          "addressRegion": "Ohio",
          "postalCode": "82632-1613",
          "addressCountry": "Pakistan"
        },
        "email": "Raoul.Mills@example.org",
        "phoneNumber": "555-783-8727",
        "faxNumber": "555-657-9664"
      },
      "vesselNumber": "ACMECarrierVessel#622",
      "arrivalDate": "2021-03-09",
      "stopType": "Stopover"
    },
    "masterWayBill": "No",
    "wayBillVCID": [
      "https://vc.example.com/?queryID=0x3FeF56faBFe0d9D21b7058F48bAFfB4C5d60945E08D2Ff76750FeCC83F3eBAd0"
    ],
    "packageVCID": [
      "https://vc.example.com/?queryID=0x1feCB1eAaCE66e069F00Ec43BfB345da1Ea403EAFb4E43Ae55D3cf7dCAa6E9E8",
      "https://vc.example.com/?queryID=0x3F06F6D71cC5aE55DD42Ee4Dd34Fc9fE4eb6a416C273c2b9bB23929eA4C2b31E",
      "https://vc.example.com/?queryID=0x5C372e8b5e4f1d05203a9Dbc3C9F734f0eaFfF4f25DB624BCEB89da94916cA2E",
      "https://vc.example.com/?queryID=0x9EE3ED5Ad5a1D55E0d3f756fB0e86da32CD5EeF8Dd3210cEE53C0FB4159eeF5E",
      "https://vc.example.com/?queryID=0x1bABd2FF7F13A6b245BB4851278F9db9f3DF3C160131e2AcBE5a6Ca91fdAF377",
      "https://vc.example.com/?queryID=0xAeb127cb6F0adBC97B8dDDB9fd5dE933d200eD65947A37dbD3FF4CfDe87A03f0",
      "https://vc.example.com/?queryID=0xE0dc9abb40A9Af39DA55FB8c34759d1Cc9d5AD0eb91af41dE7fFba9a2c6EDBD9",
      "https://vc.example.com/?queryID=0x0fdcfad41a455EC7aEabEdebD2a832Eda93B6413a8CEEfE92b810FCe76dcf29F"
    ],
    "certificateName": "ACME Carrier Ecommerce Way Bill Registration Certificate"
  }
]