[
  {
    "organizationName": "Hettinger Group",
    "streetAddress": "55790 Sierra Parkways",
    "addressRegion": "Mississippi",
    "postalCode": "84478",
    "addressCountry": "Macedonia",
    "panel": "quantify",
    "feed": "reboot",
    "matrix": "back up"
  },
  {
    "streetAddress": "617 Grant Locks",
    "addressLocality": "Bellachester",
    "addressRegion": "Rhode Island",
    "addressCountry": "United States Minor Outlying Islands",
    "system": "bypass",
    "transmitter": "parse",
    "microchip": "back up"
  },
  {
    "@context": [
      "https://w3id.org/traceability/v1"
    ],
    "type": "PostalAddress",
    "streetAddress": "8340 Zola Route",
    "addressLocality": "Yesseniaburgh",
    "addressRegion": "Pennsylvania",
    "postalCode": "73248-5419",
    "addressCountry": "Ukraine",
    "protocol": "quantify",
    "interface": "index"
  }
]