[
  {
    "@context": [
      "https://w3id.org/traceability/v1"
    ],
    "type": "PostalAddress",
    "organizationName": "Kuhlman - Williamson",
    "streetAddress": "7276 Harry Forges",
    "addressLocality": "North Amarastad",
    "addressRegion": "Texas",
    "postalCode": "08986",
    "addressCountry": "Malaysia"
  },
  {
    "@context": [
      "https://w3id.org/traceability/v1"
    ],
    "type": "PostalAddress",
    "organizationName": "Conn - Rath",
    "streetAddress": "3155 Jakob Shoals",
    "addressLocality": "New Alfonso",
    "addressRegion": "South Carolina",
    "postalCode": "20075",
    "addressCountry": "Georgia"
  },
  {
    "@context": [
      "https://w3id.org/traceability/v1"
    ],
    "type": "PostalAddress",
    "organizationName": "Funk Inc",
    "streetAddress": "513 Sauer Ridges",
    "addressLocality": "Ernieport",
    "addressRegion": "Kentucky",
    "postalCode": "55872-7955",
    "addressCountry": "Palau"
  }
]