[
  {
    "@context": [
      "https://w3id.org/traceability/v1"
    ],
    "type": "ShippingStop",
    "shippingStopAddress": {
      "type": "PostalAddress",
      "organizationName": "Kohler Inc",
      "streetAddress": "198 Leanna Spur",
      "addressLocality": "Jackelineland",
      "addressRegion": "Louisiana",
      "postalCode": "97685-0260",
      "addressCountry": "Andorra"
    },
    "carrier": {
      "type": "Organization",
      "name": "Jacobi, Stark and Dach",
      "description": "Open-architected exuding paradigm",
      "address": {
        "type": "PostalAddress",
        "streetAddress": "1178 Shanahan Circle",
        "addressLocality": "Gibsonland",
        "addressRegion": "Ohio",
        "postalCode": "97315-5431",
        "addressCountry": "China"
      },
      "email": "Precious_Hettinger@example.net",
      "phoneNumber": "555-631-8732",
      "faxNumber": "555-768-4631"
    },
    "vesselNumber": "ACMECarrierVessel#124",
    "arrivalDate": "2021-03-09",
    "stopType": "Stopover"
  },
  {
    "@context": [
      "https://w3id.org/traceability/v1"
    ],
    "type": "ShippingStop",
    "shippingStopAddress": {
      "type": "PostalAddress",
      "organizationName": "Schmidt - Auer",
      "streetAddress": "11799 McKenzie Shore",
      "addressLocality": "Lake Fosterview",
      "addressRegion": "Alabama",
      "postalCode": "13729-7045",
      "addressCountry": "Wallis and Futuna"
    },
    "carrier": {
      "type": "Organization",
      "name": "Haley - Roob",
      "description": "Innovative mission-critical access",
      "address": {
        "type": "PostalAddress",
        "streetAddress": "295 Schmeler Forest",
        "addressLocality": "South Brianne",
        "addressRegion": "Virginia",
        "postalCode": "41784",
        "addressCountry": "Pitcairn Islands"
      },
      "email": "Modesto.Grady@example.net",
      "phoneNumber": "555-305-8816",
      "faxNumber": "555-279-4451"
    },
    "vesselNumber": "ACMECarrierVessel#320",
    "arrivalDate": "2021-03-09",
    "stopType": "Departure"
  },
  {
    "@context": [
      "https://w3id.org/traceability/v1"
    ],
    "type": "ShippingStop",
    "shippingStopAddress": {
      "type": "PostalAddress",
      "organizationName": "Zboncak - Moore",
      "streetAddress": "7621 Marta Skyway",
      "addressLocality": "West Isaias",
      "addressRegion": "Nevada",
      "postalCode": "19448-8408",
      "addressCountry": "Suriname"
    },
    "carrier": {
      "type": "Organization",
      "name": "Ruecker, Gibson and Gerhold",
      "description": "User-centric heuristic internet solution",
      "address": {
        "type": "PostalAddress",
        "streetAddress": "5858 Carter Keys",
        "addressLocality": "Johnsonton",
        "addressRegion": "Arkansas",
        "postalCode": "06403-6953",
        "addressCountry": "Montserrat"
      },
      "email": "Rickie_Block@example.net",
      "phoneNumber": "555-782-3617",
      "faxNumber": "555-577-3398"
    },
    "vesselNumber": "ACMECarrierVessel#109",
    "arrivalDate": "2021-03-09",
    "stopType": "Destination"
  }
]