[
  {
    "@context": [
      "https://w3id.org/traceability/v1"
    ],
    "type": "LEIentity",
    "legalName": "Ernser LLC",
    "legalNameLanguage": "es_MX",
    "otherNames": [
      "Kihn, Christiansen and Toy",
      "Jenkins - Balistreri"
    ],
    "transliteratedOtherNames": [
      "Kihn, Christiansen and Toy",
      "Jenkins - Balistreri"
    ],
    "legalAddress": {
      "type": "LEIaddress",
      "language": "zh_CN",
      "addressLines": [
        "Mohr Inc",
        "06827 Durward Overpass"
      ],
      "addressNumber": "421",
      "addressNumberWithinBuilding": "1",
      "mailRouting": "369 Sawayn Cape, 80705-8268",
      "city": "Monaville",
      "region": "Berkshire",
      "country": "Wallis and Futuna",
      "postalCode": "51726-2479"
    },
    "headquartersAddress": {
      "type": "LEIaddress",
      "language": "en_AU_ocker",
      "addressLines": [
        "Bergstrom, Upton and Zulauf",
        "33885 Bettie Ford"
      ],
      "addressNumber": "368",
      "addressNumberWithinBuilding": "9",
      "mailRouting": "302 Demarco Circles, 64804-7661",
      "city": "Schneidermouth",
      "region": "Avon",
      "country": "Romania",
      "postalCode": "32549-0656"
    },
    "registrationAuthority": {
      "type": "LEIauthority",
      "validationAuthorityID": "RA000002",
      "otherValidationAuthorityID": "I85QFRCB",
      "validationAuthorityEntityID": "IHLA09R0PADJ10RAYV8L"
    },
    "legalJurisdiction": "Buckinghamshire",
    "entityCategory": "Jewelery",
    "legalForm": "CORPORATION",
    "associatedEntity": {
      "type": "Organization",
      "leiCode": "Y74H9YHDUF5P9L2APE87",
      "name": "Mayer - Padberg"
    },
    "status": "REQUESTED",
    "expirationDate": "2022-07-11",
    "expirationReason": "reinvent viral networks",
    "successorEntity": {
      "type": "Organization",
      "leiCode": "P4KNDCFQKJ0G26VM2ZPT",
      "name": "Beier, Goldner and Hirthe"
    },
    "otherAddresses": []
  },
  {
    "@context": [
      "https://w3id.org/traceability/v1"
    ],
    "type": "LEIentity",
    "legalName": "Lesch - Lubowitz",
    "legalNameLanguage": "tr",
    "otherNames": [
      "Barrows and Sons",
      "Waelchi, Turcotte and McCullough"
    ],
    "transliteratedOtherNames": [
      "Barrows and Sons",
      "Waelchi, Turcotte and McCullough"
    ],
    "legalAddress": {
      "type": "LEIaddress",
      "language": "vi",
      "addressLines": [
        "Effertz - Schoen",
        "18589 Dietrich Spur"
      ],
      "addressNumber": "238",
      "addressNumberWithinBuilding": "2",
      "mailRouting": "076 Bashirian Forge, 15761-5345",
      "city": "Lake Elmoland",
      "region": "Borders",
      "country": "Macao",
      "postalCode": "46475-7891"
    },
    "headquartersAddress": {
      "type": "LEIaddress",
      "language": "en_IND",
      "addressLines": [
        "Bernier, Pouros and Hegmann",
        "8156 Unique Viaduct"
      ],
      "addressNumber": "350",
      "addressNumberWithinBuilding": "5",
      "mailRouting": "0349 Derrick Plain, 44672",
      "city": "Millsport",
      "region": "Buckinghamshire",
      "country": "Martinique",
      "postalCode": "80244-2878"
    },
    "registrationAuthority": {
      "type": "LEIauthority",
      "validationAuthorityID": "RA000661",
      "otherValidationAuthorityID": "6OWUF37V",
      "validationAuthorityEntityID": "FBE6F8LFI95B24QAKKCF"
    },
    "legalJurisdiction": "Borders",
    "entityCategory": "Industrial",
    "legalForm": "CORPORATION",
    "associatedEntity": {
      "type": "Organization",
      "leiCode": "CGP1A68SCG6APDMUHQE9",
      "name": "Schinner, Trantow and Haag"
    },
    "status": "IN PROGRESS",
    "expirationDate": "2022-07-11",
    "expirationReason": "optimize frictionless experiences",
    "successorEntity": {
      "type": "Organization",
      "leiCode": "QE5S4ACNTV812T4KULMI",
      "name": "Swift LLC"
    },
    "otherAddresses": []
  },
  {
    "@context": [
      "https://w3id.org/traceability/v1"
    ],
    "type": "LEIentity",
    "legalName": "Ondricka, Herzog and Hermiston",
    "legalNameLanguage": "ne",
    "otherNames": [
      "Schmitt and Sons",
      "Kub - Robel"
    ],
    "transliteratedOtherNames": [
      "Schmitt and Sons",
      "Kub - Robel"
    ],
    "legalAddress": {
      "type": "LEIaddress",
      "language": "ro",
      "addressLines": [
        "Grimes - Haag",
        "2344 Pietro Summit"
      ],
      "addressNumber": "373",
      "addressNumberWithinBuilding": "1",
      "mailRouting": "252 Turner Prairie, 04247",
      "city": "Lake Breannehaven",
      "region": "Avon",
      "country": "Mexico",
      "postalCode": "41074"
    },
    "headquartersAddress": {
      "type": "LEIaddress",
      "language": "en_GB",
      "addressLines": [
        "Koss and Sons",
        "874 Kimberly Burgs"
      ],
      "addressNumber": "444",
      "addressNumberWithinBuilding": "1",
      "mailRouting": "73005 Raegan Vista, 40209",
      "city": "West Carlee",
      "region": "Buckinghamshire",
      "country": "Montenegro",
      "postalCode": "65791"
    },
    "registrationAuthority": {
      "type": "LEIauthority",
      "validationAuthorityID": "RA000004",
      "otherValidationAuthorityID": "0V8FX56R",
      "validationAuthorityEntityID": "4SKNVUHQZVOF2QZZEQA4"
    },
    "legalJurisdiction": "Borders",
    "entityCategory": "Jewelery",
    "legalForm": "CORPORATION",
    "associatedEntity": {
      "type": "Organization",
      "leiCode": "V0BIOJ0EDACOJ72SSS7E",
      "name": "Bogan - Daniel"
    },
    "status": "REQUESTED",
    "expirationDate": "2022-07-11",
    "expirationReason": "productize bleeding-edge initiatives",
    "successorEntity": {
      "type": "Organization",
      "leiCode": "U6KWZGA2AL5L52AZSJWK",
      "name": "Lebsack, Feeney and Monahan"
    },
    "otherAddresses": []
  }
]