[
  {
    "@context": [
      "https://w3id.org/traceability/v1"
    ],
    "inBondNumber": "123456789",
    "irsNumber": "12345678-01",
    "portOfEntry": "Superior, WI, USA",
    "carrier": {
      "@context": [
        "https://w3id.org/traceability/v1"
      ],
      "type": "Organization",
      "name": "Kertzmann, Stehr and Murray",
      "description": "Optional encompassing internet solution",
      "address": {
        "type": "PostalAddress",
        "streetAddress": "4262 Macejkovic Ranch",
        "addressLocality": "New Elenor",
        "addressRegion": "California",
        "postalCode": "91793-1590",
        "addressCountry": "Turkey"
      },
      "email": "Greyson49@example.org",
      "phoneNumber": "555-137-5728",
      "faxNumber": "555-325-7524"
    },
    "valuePerItem": "8499",
    "product": {
      "type": "Product",
      "manufacturer": {
        "type": "Person",
        "firstName": "Oma",
        "lastName": "Hayes",
        "email": "Enoch_Balistreri@example.net",
        "phoneNumber": "555-785-6083",
        "worksFor": {
          "type": "Organization",
          "name": "Waters, Yost and Franecki",
          "description": "Optional logistical definition",
          "address": {
            "type": "PostalAddress",
            "streetAddress": "7008 Hilll Rapids",
            "addressLocality": "Lake Jakob",
            "addressRegion": "Wisconsin",
            "postalCode": "18398",
            "addressCountry": "French Southern Territories"
          },
          "email": "Granville0@example.org",
          "phoneNumber": "555-339-8775",
          "faxNumber": "555-293-8033"
        },
        "jobTitle": "Internal Implementation Orchestrator"
      },
      "name": "Crude Oil Barrel",
      "description": "Heavy Sour Dilbit",
      "sizeOrAmount": {
        "type": "QuantitativeValue",
        "unitCode": "hg/ha",
        "value": "8534"
      },
      "weight": {
        "type": "QuantitativeValue",
        "unitCode": "hg/ha",
        "value": "2653"
      },
      "sku": "654569647803"
    },
    "alarm": "override",
    "matrix": "hack",
    "panel": "copy"
  },
  {
    "@context": [
      "https://w3id.org/traceability/v1"
    ],
    "portOfEntry": "Superior, WI, USA",
    "recipient": {
      "@context": [
        "https://w3id.org/traceability/v1"
      ],
      "type": "Person",
      "firstName": "Heber",
      "lastName": "Hermann",
      "email": "Gwen_Berge@example.com",
      "phoneNumber": "555-669-4699",
      "worksFor": {
        "type": "Organization",
        "name": "Weimann - Jakubowski",
        "description": "Operative cohesive matrices",
        "address": {
          "type": "PostalAddress",
          "streetAddress": "992 Nathen Forge",
          "addressLocality": "Jovanfurt",
          "addressRegion": "Indiana",
          "postalCode": "75576",
          "addressCountry": "Kuwait"
        },
        "email": "Alexandrea73@example.net",
        "phoneNumber": "555-390-8139",
        "faxNumber": "555-533-4238"
      },
      "jobTitle": "Global Data Designer"
    },
    "shipment": {
      "type": "DeliveryParcel",
      "originAddress": {
        "@context": [
          "https://w3id.org/traceability/v1"
        ],
        "type": "PostalAddress",
        "organizationName": "Raynor, Sawayn and Ledner",
        "streetAddress": "079 Eugenia Falls",
        "addressLocality": "Janessafort",
        "addressRegion": "Kentucky",
        "postalCode": "74371-6389",
        "addressCountry": "Sierra Leone"
      },
      "deliveryAddress": {
        "@context": [
          "https://w3id.org/traceability/v1"
        ],
        "type": "PostalAddress",
        "organizationName": "Bauch LLC",
        "streetAddress": "4001 Maye Meadow",
        "addressLocality": "Langworthland",
        "addressRegion": "Utah",
        "postalCode": "29089",
        "addressCountry": "Macao"
      },
      "deliveryMethod": "pipeline"
    },
    "totalOrderValue": "54743",
    "pixel": "copy"
  },
  {
    "@context": [
      "https://w3id.org/traceability/v1"
    ],
    "inBondType": "IT (61)",
    "portOfEntry": "Superior, WI, USA",
    "carrier": {
      "@context": [
        "https://w3id.org/traceability/v1"
      ],
      "type": "Person",
      "firstName": "Timmothy",
      "lastName": "Kuvalis",
      "email": "Jovan.Toy@example.com",
      "phoneNumber": "555-909-5062",
      "worksFor": {
        "type": "Organization",
        "name": "Schamberger, Champlin and Nicolas",
        "description": "Compatible intangible matrices",
        "address": {
          "type": "PostalAddress",
          "streetAddress": "973 Upton Passage",
          "addressLocality": "Tryciafort",
          "addressRegion": "Arkansas",
          "postalCode": "46053",
          "addressCountry": "Georgia"
        },
        "email": "Juvenal82@example.com",
        "phoneNumber": "555-583-5062",
        "faxNumber": "555-919-3222"
      },
      "jobTitle": "Future Mobility Liaison"
    },
    "recipient": {
      "@context": [
        "https://w3id.org/traceability/v1"
      ],
      "type": "Person",
      "firstName": "Allison",
      "lastName": "Jacobson",
      "email": "Miguel.Friesen21@example.com",
      "phoneNumber": "555-376-8493",
      "worksFor": {
        "type": "Organization",
        "name": "Kulas Inc",
        "description": "Universal heuristic infrastructure",
        "address": {
          "type": "PostalAddress",
          "streetAddress": "240 Fredrick Rue",
          "addressLocality": "North Linnieton",
          "addressRegion": "Kentucky",
          "postalCode": "16430",
          "addressCountry": "Paraguay"
        },
        "email": "Israel53@example.org",
        "phoneNumber": "555-856-7287",
        "faxNumber": "555-562-7335"
      },
      "jobTitle": "Legacy Data Director"
    },
    "shipment": {
      "type": "DeliveryParcel",
      "originAddress": {
        "@context": [
          "https://w3id.org/traceability/v1"
        ],
        "type": "PostalAddress",
        "organizationName": "Prosacco, Koelpin and Reichel",
        "streetAddress": "720 Wilton Groves",
        "addressLocality": "Sipesside",
        "addressRegion": "Mississippi",
        "postalCode": "59884",
        "addressCountry": "Sri Lanka"
      },
      "deliveryAddress": {
        "@context": [
          "https://w3id.org/traceability/v1"
        ],
        "type": "PostalAddress",
        "organizationName": "Botsford Group",
        "streetAddress": "591 Keyon Ranch",
        "addressLocality": "Port Selmer",
        "addressRegion": "Minnesota",
        "postalCode": "58459",
        "addressCountry": "India"
      },
      "deliveryMethod": "pipeline"
    },
    "billOfLadingNumber": "123456789",
    "valuePerItem": "7816",
    "totalOrderValue": "31797",
    "system": "input",
    "firewall": "index"
  }
]