[
  {
    "system": "transmit",
    "bus": "transmit",
    "array": "parse"
  },
  {
    "@context": [
      "https://w3id.org/traceability/v1"
    ],
    "type": "EcommerceWayBillRegistrationEvidenceDocument",
    "waybillType": "Single",
    "issuer": {
      "type": "Organization",
      "name": "Olson LLC",
      "description": "Down-sized intermediate array",
      "address": {
        "type": "PostalAddress",
        "streetAddress": "7580 Godfrey Summit",
        "addressLocality": "North Aiyana",
        "addressRegion": "Massachusetts",
        "postalCode": "63457",
        "addressCountry": "Democratic People's Republic of Korea"
      },
      "email": "Laury_Greenholt@example.org",
      "phoneNumber": "555-421-6572",
      "faxNumber": "555-671-5322"
    },
    "sidNumber": "",
    "consignee": {
      "type": "Organization",
      "name": "Schultz, Morar and Metz",
      "description": "Function-based fault-tolerant collaboration",
      "address": {
        "type": "PostalAddress",
        "streetAddress": "647 Rupert Ridges",
        "addressLocality": "Johnsonmouth",
        "addressRegion": "Kansas",
        "postalCode": "96504",
        "addressCountry": "Tokelau"
      },
      "email": "Kaylee.Steuber@example.com",
      "phoneNumber": "555-260-2074",
      "faxNumber": "555-197-3950"
    },
    "cidNumber": "",
    "issuerAgent": {
      "type": "IssuerAgent",
      "issuerAgentOrg": {
        "type": "Organization",
        "name": "Ward, Orn and Ritchie",
        "description": "Mandatory disintermediate time-frame",
        "address": {
          "type": "PostalAddress",
          "streetAddress": "07386 Keeling Estate",
          "addressLocality": "Cummeratamouth",
          "addressRegion": "Oklahoma",
          "postalCode": "51611-2250",
          "addressCountry": "Saint Helena"
        },
        "email": "Miller.Predovic52@example.org",
        "phoneNumber": "555-389-8528",
        "faxNumber": "555-603-7339"
      },
      "iataCode": "IATA#266",
      "accountNumber": "",
      "accountingInformation": "Please charge to Account 123 and Account 321",
      "charge": {
        "@context": [
          "https://w3id.org/traceability/v1"
        ],
        "type": "PriceSpecification",
        "price": 8219,
        "priceCurrency": "AMD"
      },
      "declaredValueCarriage": {
        "@context": [
          "https://w3id.org/traceability/v1"
        ],
        "type": "PriceSpecification",
        "price": 1022,
        "priceCurrency": "PKR"
      },
      "declaredValueCarriagePaymentStatus": "PaymentAutomaticallyApplied",
      "declaredValueCustoms": {
        "@context": [
          "https://w3id.org/traceability/v1"
        ],
        "type": "PriceSpecification",
        "price": 7921,
        "priceCurrency": "BIF"
      },
      "declaredValueCustomsPaymentStatus": "PaymentAutomaticallyApplied",
      "amountInsurance": {
        "@context": [
          "https://w3id.org/traceability/v1"
        ],
        "type": "PriceSpecification",
        "price": 8118,
        "priceCurrency": "ETB"
      }
    },
    "shippingRoute": [
      {
        "type": "ShippingStop",
        "shippingStopAddress": {
          "type": "PostalAddress",
          "organizationName": "Maggio - Beer",
          "streetAddress": "1173 Stanford Road",
          "addressLocality": "McCulloughchester",
          "addressRegion": "Connecticut",
          "postalCode": "17751-1364",
          "addressCountry": "Netherlands Antilles"
        },
        "carrier": {
          "type": "Organization",
          "name": "Trantow, Walker and Howell",
          "description": "Object-based discrete flexibility",
          "address": {
            "type": "PostalAddress",
            "streetAddress": "4523 Monroe Crest",
            "addressLocality": "Lake Quintenberg",
            "addressRegion": "Georgia",
            "postalCode": "03456-8472",
            "addressCountry": "Singapore"
          },
          "email": "Myra86@example.net",
          "phoneNumber": "555-602-2231",
          "faxNumber": "555-412-1627"
        },
        "vesselNumber": "ACMECarrierVessel#480",
        "arrivalDate": "2021-03-09",
        "stopType": "Departure"
      },
      {
        "type": "ShippingStop",
        "shippingStopAddress": {
          "type": "PostalAddress",
          "organizationName": "Stehr - Waelchi",
          "streetAddress": "00567 Hane Centers",
          "addressLocality": "New Warrenborough",
          "addressRegion": "Montana",
          "postalCode": "62244",
          "addressCountry": "Kuwait"
        },
        "carrier": {
          "type": "Organization",
          "name": "Hoppe, Carroll and Reichel",
          "description": "Automated intermediate help-desk",
          "address": {
            "type": "PostalAddress",
            "streetAddress": "148 Buckridge Summit",
            "addressLocality": "East Joannyfort",
            "addressRegion": "Rhode Island",
            "postalCode": "09541",
            "addressCountry": "Serbia"
          },
          "email": "Rosalia10@example.net",
          "phoneNumber": "555-132-4620",
          "faxNumber": "555-147-4824"
        },
        "vesselNumber": "ACMECarrierVessel#427",
        "arrivalDate": "2021-03-09",
        "stopType": "Destination"
      },
      {
        "type": "ShippingStop",
        "shippingStopAddress": {
          "type": "PostalAddress",
          "organizationName": "Morissette and Sons",
          "streetAddress": "535 Heller Ports",
          "addressLocality": "New Bennie",
          "addressRegion": "Vermont",
          "postalCode": "20479",
          "addressCountry": "Venezuela"
        },
        "carrier": {
          "type": "Organization",
          "name": "D'Amore - Veum",
          "description": "Optimized mission-critical challenge",
          "address": {
            "type": "PostalAddress",
            "streetAddress": "6275 Lon Glen",
            "addressLocality": "Jacklynburgh",
            "addressRegion": "Missouri",
            "postalCode": "72213",
            "addressCountry": "Bermuda"
          },
          "email": "Anissa34@example.com",
          "phoneNumber": "555-932-4772",
          "faxNumber": "555-150-2019"
        },
        "vesselNumber": "ACMECarrierVessel#228",
        "arrivalDate": "2021-03-09",
        "stopType": "Stopover"
      }
    ],
    "handlingInstructions": "Forward on to Example Forwarder in the US",
    "handlingInstructionsSCI": "",
    "wayBillCommodityContent": {
      "type": "EcommerceWayBillCommodityContent",
      "wayBillGrouping": [
        {
          "type": "EcommerceWayBillCommodityGroup",
          "commodityItemNumber": "k3ir3w0qyjdu",
          "natureQuantityOfGoods": "A lot of laptops that way a lot",
          "totalsCommodityGroup": {
            "type": "EcommerceWayBillTotals",
            "totalPieces": 607,
            "weight": 697969,
            "chargeableWeight": 628172.1,
            "weightUnit": "kg",
            "rateCharge": 0.00018307084953311364,
            "totalRateCharge": {
              "type": "PriceSpecification",
              "price": 115,
              "priceCurrency": "AZN"
            }
          }
        },
        {
          "type": "EcommerceWayBillCommodityGroup",
          "commodityItemNumber": "xukc41kqrse5",
          "natureQuantityOfGoods": "A lot fo stuffed animals, and toys and other useless stuff that weighs a lot",
          "totalsCommodityGroup": {
            "type": "EcommerceWayBillTotals",
            "totalPieces": 881,
            "weight": 541967,
            "chargeableWeight": 487770.3,
            "weightUnit": "kg",
            "rateCharge": 0.003950630040410415,
            "totalRateCharge": {
              "type": "PriceSpecification",
              "price": 1927,
              "priceCurrency": "NGN"
            }
          }
        },
        {
          "type": "EcommerceWayBillCommodityGroup",
          "commodityItemNumber": "m94bbu7hwore",
          "natureQuantityOfGoods": "A lot of laptops that way a lot",
          "totalsCommodityGroup": {
            "type": "EcommerceWayBillTotals",
            "totalPieces": 680,
            "weight": 305027,
            "chargeableWeight": 274524.3,
            "weightUnit": "lb",
            "rateCharge": 0.022799438883916653,
            "totalRateCharge": {
              "type": "PriceSpecification",
              "price": 6259,
              "priceCurrency": "ERN"
            }
          }
        }
      ],
      "totalsCommodityContent": {
        "type": "EcommerceWayBillTotals",
        "totalPieces": 759,
        "weight": 379270,
        "chargeableWeight": 341343,
        "weightUnit": "lb",
        "rateCharge": 0.006146310309571311,
        "totalRateCharge": {
          "type": "PriceSpecification",
          "price": 2098,
          "priceCurrency": "KHR"
        }
      }
    },
    "matrix": "index",
    "bus": "quantify",
    "transmitter": "back up",
    "card": "back up"
  },
  {
    "waybillType": "Single",
    "shipper": {
      "type": "Organization",
      "name": "White, Littel and Erdman",
      "description": "Profound eco-centric definition",
      "address": {
        "type": "PostalAddress",
        "streetAddress": "73033 Doyle Forest",
        "addressLocality": "Port Willy",
        "addressRegion": "Virginia",
        "postalCode": "07394-3286",
        "addressCountry": "Jamaica"
      },
      "email": "Larue_Huels@example.net",
      "phoneNumber": "555-676-8825",
      "faxNumber": "555-865-2625"
    },
    "shippingRoute": [
      {
        "type": "ShippingStop",
        "shippingStopAddress": {
          "type": "PostalAddress",
          "organizationName": "Berge - Becker",
          "streetAddress": "935 Kuvalis Knoll",
          "addressLocality": "Lake Ruthie",
          "addressRegion": "North Carolina",
          "postalCode": "61115",
          "addressCountry": "French Guiana"
        },
        "carrier": {
          "type": "Organization",
          "name": "Beatty, Lebsack and Boyer",
          "description": "Cross-platform non-volatile time-frame",
          "address": {
            "type": "PostalAddress",
            "streetAddress": "20103 Reggie Isle",
            "addressLocality": "North Yadira",
            "addressRegion": "Minnesota",
            "postalCode": "31084",
            "addressCountry": "Kiribati"
          },
          "email": "Lottie.Denesik7@example.org",
          "phoneNumber": "555-329-7387",
          "faxNumber": "555-416-9853"
        },
        "vesselNumber": "ACMECarrierVessel#31",
        "arrivalDate": "2021-03-09",
        "stopType": "Departure"
      }
    ],
    "firewall": "connect",
    "feed": "synthesize"
  }
]