{
  "@context": [
    "https://www.w3.org/2018/credentials/v1",
    "https://w3id.org/traceability/v1"
  ],
  "id": "http://example.org/credentials/",
  "type": [
    "VerifiableCredential"
  ],
  "issuanceDate": "2021-02-04T20:29:37+00:00",
  "issuer": "did:example:123",
  "credentialSubject": {
    "@context": [
      "https://w3id.org/traceability/v1"
    ],
    "type": "EcommerceWayBillCommodityContent",
    "wayBillGrouping": [
      {
        "type": "EcommerceWayBillCommodityGroup",
        "commodityItemNumber": "k9rw4dij713f",
        "natureQuantityOfGoods": "A lot of laptops that way a lot",
        "totalsCommodityGroup": {
          "type": "EcommerceWayBillTotals",
          "totalPieces": 416,
          "weight": 834040,
          "chargeableWeight": 750636,
          "weightUnit": "lb",
          "rateCharge": 0.010736229011131894,
          "totalRateCharge": {
            "type": "PriceSpecification",
            "price": 8059,
            "priceCurrency": "BYN"
          }
        }
      },
      {
        "type": "EcommerceWayBillCommodityGroup",
        "commodityItemNumber": "b89t3x336g1c",
        "natureQuantityOfGoods": "A lot of laptops that way a lot",
        "totalsCommodityGroup": {
          "type": "EcommerceWayBillTotals",
          "totalPieces": 630,
          "weight": 871982,
          "chargeableWeight": 784783.8,
          "weightUnit": "lb",
          "rateCharge": 0.0010754554311646087,
          "totalRateCharge": {
            "type": "PriceSpecification",
            "price": 844,
            "priceCurrency": "EGP"
          }
        }
      },
      {
        "type": "EcommerceWayBillCommodityGroup",
        "commodityItemNumber": "brn1vhrfqche",
        "natureQuantityOfGoods": "A lot fo stuffed animals, and toys and other useless stuff that weighs a lot",
        "totalsCommodityGroup": {
          "type": "EcommerceWayBillTotals",
          "totalPieces": 697,
          "weight": 534641,
          "chargeableWeight": 481176.9,
          "weightUnit": "lb",
          "rateCharge": 0.00337090163721492,
          "totalRateCharge": {
            "type": "PriceSpecification",
            "price": 1622,
            "priceCurrency": "LYD"
          }
        }
      }
    ],
    "totalsCommodityContent": {
      "type": "EcommerceWayBillTotals",
      "totalPieces": 216,
      "weight": 807378,
      "chargeableWeight": 726640.2000000001,
      "weightUnit": "kg",
      "rateCharge": 0.010464601325387722,
      "totalRateCharge": {
        "type": "PriceSpecification",
        "price": 7604,
        "priceCurrency": "ERN"
      }
    }
  }
}