[
  {
    "@context": [
      "https://w3id.org/traceability/v1"
    ],
    "trackingID": "567302113957",
    "certificateName": "ACME Carrier Ecommerce Package Registration Certificate",
    "microchip": "bypass"
  },
  {
    "@context": [
      "https://w3id.org/traceability/v1"
    ],
    "trackingID": "990295980055",
    "protocol": "navigate",
    "system": "override"
  },
  {
    "type": "EcommercePackageRegistrationCredential",
    "trackingID": "841390655701",
    "certificateName": "ACME Carrier Ecommerce Package Registration Certificate",
    "transmitter": "transmit",
    "application": "parse",
    "microchip": "transmit"
  }
]