[
  {
    "@context": [
      "https://w3id.org/traceability/v1"
    ],
    "type": "Customer",
    "name": "Rosario Trantow",
    "address": {
      "type": "PostalAddress",
      "streetAddress": "12358 Nicolas Burgs",
      "addressLocality": "West Annieburgh",
      "addressRegion": "West Virginia",
      "postalCode": "54408-8803",
      "addressCountry": "Reunion"
    },
    "telephone": "555-913-9518",
    "email": "Heaven_Ruecker47@example.com"
  },
  {
    "@context": [
      "https://w3id.org/traceability/v1"
    ],
    "type": "Customer",
    "name": "Lucile Robel",
    "address": {
      "type": "PostalAddress",
      "streetAddress": "11339 Gussie Wells",
      "addressLocality": "Ernsermouth",
      "addressRegion": "Rhode Island",
      "postalCode": "55163",
      "addressCountry": "Belarus"
    },
    "telephone": "555-758-6967",
    "email": "Rosetta_Rowe@example.com"
  },
  {
    "@context": [
      "https://w3id.org/traceability/v1"
    ],
    "type": "Customer",
    "name": "Rowan Stoltenberg",
    "address": {
      "type": "PostalAddress",
      "streetAddress": "81777 Howell Radial",
      "addressLocality": "Loweport",
      "addressRegion": "Kansas",
      "postalCode": "41573",
      "addressCountry": "Russian Federation"
    },
    "telephone": "555-212-7560",
    "email": "Dorothea.Bartell19@example.com"
  }
]