[
  {
    "microchip": "input"
  },
  {
    "@context": [
      "https://w3id.org/traceability/v1"
    ],
    "lei": "VUHQZVOF2QZZEQA4KIAL",
    "bic": [
      "LMFECNCUOQ"
    ],
    "application": "back up"
  },
  {
    "@context": [
      "https://w3id.org/traceability/v1"
    ],
    "lei": "GUX0XX73CU5HINGIWHXU",
    "entity": {
      "@context": [
        "https://w3id.org/traceability/v1"
      ],
      "type": "LEIentity",
      "legalName": "Schmidt, Stark and Hodkiewicz",
      "legalNameLanguage": "ko",
      "otherNames": [
        "Gislason, Runolfsdottir and Bechtelar",
        "Feeney - Goodwin"
      ],
      "transliteratedOtherNames": [
        "Gislason, Runolfsdottir and Bechtelar",
        "Feeney - Goodwin"
      ],
      "legalAddress": {
        "type": "LEIaddress",
        "language": "tr",
        "addressLines": [
          "Bernhard - Wolff",
          "2317 Talon Isle"
        ],
        "addressNumber": "464",
        "addressNumberWithinBuilding": "3",
        "mailRouting": "6048 Amalia View, 28586",
        "city": "Aliviafurt",
        "region": "Bedfordshire",
        "country": "Azerbaijan",
        "postalCode": "36267"
      },
      "headquartersAddress": {
        "type": "LEIaddress",
        "language": "ko",
        "addressLines": [
          "Hammes, O'Keefe and Botsford",
          "94403 Geovanni Parkway"
        ],
        "addressNumber": "80",
        "addressNumberWithinBuilding": "2",
        "mailRouting": "7338 Kale Pike, 00052-7811",
        "city": "New Shanonshire",
        "region": "Berkshire",
        "country": "Lithuania",
        "postalCode": "77249"
      },
      "registrationAuthority": {
        "type": "LEIauthority",
        "validationAuthorityID": "RA000005",
        "otherValidationAuthorityID": "G30GTVCN",
        "validationAuthorityEntityID": "JEOAPDYIJBEYYXNVAF4O"
      },
      "legalJurisdiction": "Berkshire",
      "entityCategory": "Finance",
      "legalForm": "CORPORATION",
      "associatedEntity": {
        "type": "Organization",
        "leiCode": "DRHHW4T40SBJFH8O7U1M",
        "name": "Olson, Jerde and Kovacek"
      },
      "status": "REQUESTED",
      "expirationDate": "2022-07-11",
      "expirationReason": "reinvent robust e-commerce",
      "successorEntity": {
        "type": "Organization",
        "leiCode": "K2NEUJAF6QDTCR41O6IJ",
        "name": "Weber, Herman and Skiles"
      },
      "otherAddresses": []
    },
    "bic": [
      "FGGASJFBIN"
    ],
    "monitor": "generate"
  }
]