{
  "@context": [
    "https://www.w3.org/2018/credentials/v1",
    "https://w3id.org/traceability/v1"
  ],
  "id": "http://example.org/credentials/",
  "type": [
    "VerifiableCredential"
  ],
  "issuanceDate": "2021-02-04T20:29:37+00:00",
  "issuer": "did:example:123",
  "credentialSubject": {
    "@context": [
      "https://w3id.org/traceability/v1"
    ],
    "type": "LEIevidenceDocument",
    "lei": "CFHJILB9QEVSXXSVUKJE",
    "entity": {
      "@context": [
        "https://w3id.org/traceability/v1"
      ],
      "type": "LEIentity",
      "legalName": "Kemmer - Schaefer",
      "legalNameLanguage": "cz",
      "otherNames": [
        "Brown - Murazik",
        "Hickle and Sons"
      ],
      "transliteratedOtherNames": [
        "Brown - Murazik",
        "Hickle and Sons"
      ],
      "legalAddress": {
        "type": "LEIaddress",
        "language": "ro",
        "addressLines": [
          "Williamson, Kautzer and Senger",
          "000 Pete Branch"
        ],
        "addressNumber": "159",
        "addressNumberWithinBuilding": "2",
        "mailRouting": "451 Leuschke Causeway, 98578-4859",
        "city": "Russelshire",
        "region": "Borders",
        "country": "Greece",
        "postalCode": "22801-5216"
      },
      "headquartersAddress": {
        "type": "LEIaddress",
        "language": "zh_CN",
        "addressLines": [
          "Greenfelder - Waters",
          "99931 Breitenberg Junctions"
        ],
        "addressNumber": "194",
        "addressNumberWithinBuilding": "6",
        "mailRouting": "6129 Lane Passage, 71705",
        "city": "Harrisville",
        "region": "Avon",
        "country": "Swaziland",
        "postalCode": "43455-4082"
      },
      "registrationAuthority": {
        "type": "LEIauthority",
        "validationAuthorityID": "RA000002",
        "otherValidationAuthorityID": "FXDWOSL0",
        "validationAuthorityEntityID": "3BIMQ9ZWMMD28WVYT28J"
      },
      "legalJurisdiction": "Buckinghamshire",
      "entityCategory": "Industrial",
      "legalForm": "LLC",
      "associatedEntity": {
        "type": "Organization",
        "leiCode": "TBA4E3BOG9A9YZB635I3",
        "name": "Haley - Daugherty"
      },
      "status": "CONFIRMED",
      "expirationDate": "2022-07-11",
      "expirationReason": "incubate intuitive methodologies",
      "successorEntity": {
        "type": "Organization",
        "leiCode": "9IF2QMCCBUAFH666HRP9",
        "name": "Runolfsson Inc"
      },
      "otherAddresses": []
    },
    "registration": {
      "@context": [
        "https://w3id.org/traceability/v1"
      ],
      "type": "LEIregistration",
      "initialRegistrationDate": "2020-01-01",
      "lastUpdateDate": "2020-01-01",
      "status": "REQUESTED",
      "nextRenewalDate": "2021-02-02",
      "managingLou": "UDAUINKMFRFWAQQTGTBJ",
      "validationSources": "FULLY_CORROBORATED",
      "validationAuthority": [
        {
          "type": "LEIauthority",
          "validationAuthorityID": "RA000005",
          "otherValidationAuthorityID": "72BJGUX0",
          "validationAuthorityEntityID": "XX73CU5HINGIWHXUDRHH"
        }
      ]
    },
    "bic": [
      "HUUWGYZPBD"
    ]
  }
}